[
  {
    "id": 1,
    "athlete_id": 2,
    "athlete_name": "Elena Rodriguez",
    "injury_type": "Knee Strain",
    "osics_code": "KNES01",
    "body_part": "Knee",
    "body_region": "Lower Limb",
    "side": "Left",
    "pathology": "Muscle/Tendon",
    "mechanism": "Non-contact",
    "severity": "Minor",
    "occurrence_date": "2024-01-10",
    "rtp_date": "2024-01-25",
    "days_lost": 15,
    "status": "Recovering",
    "treatment_sessions": 8,
    "last_treatment": "2024-01-14",
    "treating_physician": "Dr. Sarah Mitchell",
    "notes": "Grade 1 MCL strain sustained during training. Progressing well with physiotherapy.",
    "created_at": "2024-01-10T15:30:00Z",
    "updated_at": "2024-01-14T11:45:00Z"
  },
  {
    "id": 2,
    "athlete_id": 7,
    "athlete_name": "James Wilson",
    "injury_type": "Hamstring Strain",
    "osics_code": "THPS01",
    "body_part": "Hamstring",
    "body_region": "Lower Limb",
    "side": "Right",
    "pathology": "Muscle/Tendon",
    "mechanism": "Sprint",
    "severity": "Moderate",
    "occurrence_date": "2023-12-15",
    "rtp_date": "2024-01-08",
    "days_lost": 24,
    "status": "Returned",
    "treatment_sessions": 15,
    "last_treatment": "2024-01-05",
    "treating_physician": "Dr. Michael Thompson",
    "notes": "Grade 2 hamstring strain. Full recovery achieved with progressive loading program.",
    "created_at": "2023-12-15T09:20:00Z",
    "updated_at": "2024-01-08T14:15:00Z"
  },
  {
    "id": 3,
    "athlete_id": 1,
    "athlete_name": "Marcus Johnson",
    "injury_type": "Ankle Sprain",
    "osics_code": "AKLS01",
    "body_part": "Ankle",
    "body_region": "Lower Limb",
    "side": "Left",
    "pathology": "Joint/Ligament",
    "mechanism": "Contact",
    "severity": "Minor",
    "occurrence_date": "2023-11-22",
    "rtp_date": "2023-12-05",
    "days_lost": 13,
    "status": "Returned",
    "treatment_sessions": 6,
    "last_treatment": "2023-12-01",
    "treating_physician": "Dr. Sarah Mitchell",
    "notes": "Grade 1 lateral ankle sprain. Quick recovery with early mobilization.",
    "created_at": "2023-11-22T16:45:00Z",
    "updated_at": "2023-12-05T10:30:00Z"
  },
  {
    "id": 4,
    "athlete_id": 4,
    "athlete_name": "Sarah Williams",
    "injury_type": "Concussion",
    "osics_code": "HCON01",
    "body_part": "Head",
    "body_region": "Head/Neck",
    "side": "Not applicable",
    "pathology": "Central/Peripheral Nervous System",
    "mechanism": "Contact",
    "severity": "Moderate",
    "occurrence_date": "2023-10-08",
    "rtp_date": "2023-10-25",
    "days_lost": 17,
    "status": "Returned",
    "treatment_sessions": 12,
    "last_treatment": "2023-10-23",
    "treating_physician": "Dr. Jennifer Adams",
    "notes": "Sport-related concussion. Completed graduated return-to-play protocol.",
    "created_at": "2023-10-08T11:15:00Z",
    "updated_at": "2023-10-25T13:20:00Z"
  },
  {
    "id": 5,
    "athlete_id": 3,
    "athlete_name": "David Chen",
    "injury_type": "Groin Strain",
    "osics_code": "HIPS01",
    "body_part": "Groin",
    "body_region": "Lower Limb",
    "side": "Right",
    "pathology": "Muscle/Tendon",
    "mechanism": "Non-contact",
    "severity": "Minor",
    "occurrence_date": "2023-09-14",
    "rtp_date": "2023-09-28",
    "days_lost": 14,
    "status": "Returned",
    "treatment_sessions": 7,
    "last_treatment": "2023-09-25",
    "treating_physician": "Dr. Michael Thompson",
    "notes": "Adductor strain. Responded well to eccentric strengthening program.",
    "created_at": "2023-09-14T14:30:00Z",
    "updated_at": "2023-09-28T09:45:00Z"
  }
]